deeplotx/__init__.py
deeplotx/encoder/__init__.py
deeplotx/encoder/encoder.py
deeplotx/encoder/long_text_encoder.py
deeplotx/encoder/longformer_encoder.py
deeplotx/ner/__init__.py
deeplotx/ner/base_ner.py
deeplotx/ner/bert_ner.py
deeplotx/ner/named_entity.py
deeplotx/ner/n2g/__init__.py
deeplotx/nn/__init__.py
deeplotx/nn/attention.py
deeplotx/nn/auto_regression.py
deeplotx/nn/base_neural_network.py
deeplotx/nn/feed_forward.py
deeplotx/nn/linear_regression.py
deeplotx/nn/logistic_regression.py
deeplotx/nn/long_context_auto_regression.py
deeplotx/nn/long_context_recursive_sequential.py
deeplotx/nn/lora.py
deeplotx/nn/multi_head_attention.py
deeplotx/nn/multi_head_feed_forward.py
deeplotx/nn/recursive_sequential.py
deeplotx/nn/roformer_encoder.py
deeplotx/nn/rope.py
deeplotx/nn/softmax_regression.py
deeplotx/similarity/__init__.py
deeplotx/similarity/distribution.py
deeplotx/similarity/set.py
deeplotx/similarity/vector.py
deeplotx/util/__init__.py
deeplotx-0.9.15.dist-info/licenses/LICENSE
deeplotx-0.9.15.dist-info/METADATA
deeplotx-0.9.15.dist-info/WHEEL
deeplotx-0.9.15.dist-info/top_level.txt
deeplotx-0.9.15.dist-info/RECORD
