Metadata-Version: 2.4
Name: deeplotx
Version: 0.9.15
Summary: An out-of-the-box long-text NLP framework.
Requires-Python: >=3.10
License-File: LICENSE
Requires-Dist: hf-xet
Requires-Dist: jupyter
Requires-Dist: numpy
Requires-Dist: protobuf
Requires-Dist: python-dotenv
Requires-Dist: sentencepiece
Requires-Dist: tiktoken
Requires-Dist: torch
Requires-Dist: transformers
Requires-Dist: typing-extensions
Requires-Dist: vortezwohl>=0.0.17
Requires-Dist: name4py>=0.1.4
Dynamic: license-file
